{
  "@timestamp": "2026-07-16T00:00:00Z",
  "event": {
    "action": "policy_violation",
    "category": [
      "configuration"
    ],
    "dataset": "watchmyai.events",
    "id": "evt-wmai-035-malicious-000",
    "kind": "alert",
    "provider": "watchmyai",
    "type": [
      "change"
    ]
  },
  "host": {
    "name": "lab-host"
  },
  "user": {
    "name": "lab-user"
  },
  "watchmyai": {
    "agent": {
      "id": "agent-lab",
      "type": "known_ai_agent"
    },
    "attribution": {
      "level": "confirmed"
    },
    "policy": {
      "violation": {
        "detected": true,
        "type": "behavioural_drift_detected"
      }
    },
    "schema": {
      "version": "1.1.0"
    },
    "session": {
      "observed_objective_hash": "sha256:6d051a7f45337cffd6c5db074fb168c2e02a2ba6f0ddc4db8985068ce06a7937"
    },
    "task": {
      "objective_hash": "sha256:7fb41b47a8074431460c4412c1dfee4fe4327e083bf6104b43e2c184f09e7a7b"
    }
  }
}
